cofi_espresso/__init__.py
cofi_espresso/_espresso_problem.py
cofi_espresso/_version.py
cofi_espresso/exceptions.py
cofi_espresso/list_problems.py
cofi_espresso/version.py
cofi_espresso/_fmm_tomography/CMakeLists.txt
cofi_espresso/_fmm_tomography/LICENCE
cofi_espresso/_fmm_tomography/README.md
cofi_espresso/_fmm_tomography/__init__.py
cofi_espresso/_fmm_tomography/_fmm_tomography.py
cofi_espresso/_fmm_tomography/fm2dss.o
cofi_espresso/_fmm_tomography/waveTracker.py
cofi_espresso/_fmm_tomography/datasets/cbmod.txt
cofi_espresso/_fmm_tomography/datasets/ttimes/receivers_InLab_lrt_r36.dat
cofi_espresso/_fmm_tomography/datasets/ttimes/receivers_crossb_nwt_r10.dat
cofi_espresso/_fmm_tomography/datasets/ttimes/sources_InLab_lrt_s500.dat
cofi_espresso/_fmm_tomography/datasets/ttimes/sources_crossb_nwt_s10.dat
cofi_espresso/_fmm_tomography/datasets/ttimes/ttimes_InLab_lrt_s500_r36.dat
cofi_espresso/_fmm_tomography/datasets/ttimes/ttimes_crossb_nwt_s10_r10.dat
cofi_espresso/_fmm_tomography/fmst/src/fm2dss.f90
cofi_espresso/_gravity_density/LICENCE
cofi_espresso/_gravity_density/README.md
cofi_espresso/_gravity_density/__init__.py
cofi_espresso/_gravity_density/_gravity_density.py
cofi_espresso/_gravity_density/data/__init__.py
cofi_espresso/_gravity_density/data/gravmodel1.txt
cofi_espresso/_gravity_density/data/testdata.txt
cofi_espresso/_machine/__init__.py
cofi_espresso/_machine/docutils.py
cofi_espresso/_pumping_test/LICENCE
cofi_espresso/_pumping_test/README.md
cofi_espresso/_pumping_test/__init__.py
cofi_espresso/_pumping_test/_pumping_test.py
cofi_espresso/_simple_regression/LICENCE
cofi_espresso/_simple_regression/README.md
cofi_espresso/_simple_regression/__init__.py
cofi_espresso/_simple_regression/_simple_regression.py
cofi_espresso/_slug_test/LICENCE
cofi_espresso/_slug_test/README.md
cofi_espresso/_slug_test/__init__.py
cofi_espresso/_slug_test/_slug_test.py
cofi_espresso/_xray_tomography/LICENCE
cofi_espresso/_xray_tomography/README.md
cofi_espresso-0.1.0.dev0.dist-info/LICENCE
cofi_espresso-0.1.0.dev0.dist-info/METADATA
cofi_espresso-0.1.0.dev0.dist-info/WHEEL
cofi_espresso-0.1.0.dev0.dist-info/top_level.txt
cofi_espresso-0.1.0.dev0.dist-info/RECORD
