Metadata-Version: 2.1
Name: cofi-espresso
Version: 0.1.0.dev0
Summary: Earth Science PRoblems for the Evaluation of Strategies, Solvers and Optimizers
Author: InLab, Espresso development team
Keywords: inversion,inference,python package,geoscience,geophysics
Classifier: Development Status :: 2 - Pre-Alpha
Classifier: Intended Audience :: Education
Classifier: Intended Audience :: Science/Research
Classifier: Programming Language :: Python
Classifier: Programming Language :: Python :: 3
Classifier: Programming Language :: Python :: 3.6
Classifier: Programming Language :: Python :: 3.7
Classifier: Programming Language :: Python :: 3.8
Classifier: Programming Language :: Python :: 3.9
Classifier: Programming Language :: Python :: 3.10
Classifier: Programming Language :: Python :: Implementation :: CPython
Classifier: Programming Language :: C
Classifier: Programming Language :: Fortran
Classifier: Topic :: Scientific/Engineering :: Physics
Classifier: License :: OSI Approved :: BSD License
Classifier: License :: Other/Proprietary License
Requires-Python: >=3.6
License-File: LICENCE
Requires-Dist: numpy (>=1.18)
Requires-Dist: scipy (>=1.0.0)
Requires-Dist: matplotlib (>=3.1)
Requires-Dist: tqdm (>=4.0)
Requires-Dist: mpmath (>=1.2.0)
